django_cd/__init__.py
django_cd/_version.py
django_cd/actions.py
django_cd/admin.py
django_cd/apps.py
django_cd/jobs.py
django_cd/models.py
django_cd/notifications.py
django_cd/tasks.py
django_cd/triggers.py
django_cd/urls.py
django_cd/views.py
django_cd/management/__init__.py
django_cd/management/commands/__init__.py
django_cd/management/commands/runjob.py
django_cd/migrations/0001_initial.py
django_cd/migrations/0002_auto_20211219_1730.py
django_cd/migrations/0003_testresult_output.py
django_cd/migrations/__init__.py
django_cd/templates/base.html
django_cd/templates/django_cd/index.html
django_cd/templates/django_cd/jobrun.html
django_cd/templates/django_cd/jobrun_report.html
django_cd/templates/django_cd/jobruns.html
django_cd/templatetags/__init__.py
django_cd/templatetags/djangocd_extras.py
django_cd-1.2.dist-info/LICENSE
django_cd-1.2.dist-info/METADATA
django_cd-1.2.dist-info/WHEEL
django_cd-1.2.dist-info/top_level.txt
django_cd-1.2.dist-info/RECORD
