Metadata-Version: 2.1
Name: django-cd
Version: 1.2
Summary: Continuous deloyment
Home-page: https://github.com/ppinard/django-cd
Author: Philippe Pinard
Author-email: philippe.pinard@gmail.com
License: MIT license
Platform: UNKNOWN
Classifier: Development Status :: 2 - Pre-Alpha
Classifier: Intended Audience :: Developers
Classifier: License :: OSI Approved :: MIT License
Classifier: Natural Language :: English
Classifier: Programming Language :: Python :: 3
Classifier: Programming Language :: Python :: 3.7
License-File: LICENSE
Requires-Dist: django
Requires-Dist: django-bootstrap5
Requires-Dist: loguru
Requires-Dist: pyyaml
Requires-Dist: yarl
Requires-Dist: pytest
Requires-Dist: huey
Requires-Dist: crontab
Provides-Extra: dev
Requires-Dist: sphinx ; extra == 'dev'
Provides-Extra: test
Requires-Dist: pytest ; extra == 'test'
Requires-Dist: pytest-cov ; extra == 'test'
Requires-Dist: pytest-django ; extra == 'test'
